ENGR131-Util-2024/__init__.py
ENGR131-Util-2024/codes.py
ENGR131-Util-2024/midterm.py
ENGR131_Util_2024/TypesQuestions.py
ENGR131_Util_2024/__init__.py
ENGR131_Util_2024/codes.py
ENGR131_Util_2024/database.py
ENGR131_Util_2024/encryption.py
ENGR131_Util_2024/junk.py
ENGR131_Util_2024/logging.py
ENGR131_Util_2024/midterm.py
ENGR131_Util_2024/package_update.py
ENGR131_Util_2024/prints.py
ENGR131_Util_2024/reading_python.py
ENGR131_Util_2024/select_many.py
ENGR131_Util_2024/shuffle.py
ENGR131_Util_2024/student_info.py
ENGR131_Util_2024/types_questions.py
ENGR131_Util_2024/update.py
ENGR131_Util_2024/util_json.py
ENGR131_Util_2024-2.0.3.dist-info/METADATA
ENGR131_Util_2024-2.0.3.dist-info/WHEEL
ENGR131_Util_2024-2.0.3.dist-info/top_level.txt
ENGR131_Util_2024-2.0.3.dist-info/RECORD
