Metadata-Version: 2.1
Name: ENGR131-Util-2024
Version: 2.0.3
Summary: Drexel Midterm Utility Functions
Author: Joshua C. Agar
Requires-Dist: cryptography
Requires-Dist: drexel-jupyter-logger >=0.0.15
Requires-Dist: ipywidgets
